README
muckrock
muckrock.py
setup.py
muckrock.egg-info/PKG-INFO
muckrock.egg-info/SOURCES.txt
muckrock.egg-info/dependency_links.txt
muckrock.egg-info/requires.txt
muckrock.egg-info/top_level.txt