Metadata-Version: 1.1
Name: muckrock
Version: 0.0.2
Summary: Get data from Muckrock
Home-page: http://github.com/tlevine/muckrock
Author: Thomas Levine
Author-email: _@thomaslevine.com
License: AGPL
Platform: UNKNOWN
Classifier: Programming Language :: Python :: 3.4
